promptwright/__init__.py
promptwright/__main__.py
promptwright/cli.py
promptwright/config.py
promptwright/constants.py
promptwright/dataset.py
promptwright/engine.py
promptwright/exceptions.py
promptwright/factory.py
promptwright/hf_hub.py
promptwright/prompts.py
promptwright/topic_graph.py
promptwright/topic_model.py
promptwright/topic_tree.py
promptwright/utils.py
promptwright-1.5.0.dist-info/METADATA
promptwright-1.5.0.dist-info/WHEEL
promptwright-1.5.0.dist-info/entry_points.txt
promptwright-1.5.0.dist-info/licenses/LICENSE
promptwright-1.5.0.dist-info/RECORD
