Metadata-Version: 2.4
Name: promptwright
Version: 1.5.0
Summary: Large Scale Topic based Synthetic Data Generation
Author-email: Luke Hinds <luke@rdrocket.com>
License-File: LICENSE
Requires-Python: >=3.11
Requires-Dist: certifi==2025.1.31
Requires-Dist: charset-normalizer==3.4.1
Requires-Dist: click>=8.1.7
Requires-Dist: datasets==4.0.0
Requires-Dist: huggingface-hub==0.34.4
Requires-Dist: idna==3.10
Requires-Dist: ipython>=9.5.0
Requires-Dist: litellm==1.77.0
Requires-Dist: mermaid-py>=0.8.0
Requires-Dist: pydantic>=2.0.0
Requires-Dist: pyyaml>=6.0.1
Requires-Dist: requests==2.32.3
Requires-Dist: tqdm==4.67.1
Requires-Dist: urllib3==2.4.0
Provides-Extra: dev
Requires-Dist: bandit>=1.7.10; extra == 'dev'
Requires-Dist: black<26.0,>=24.10; extra == 'dev'
Requires-Dist: mermaid-py>=0.2.0; extra == 'dev'
Requires-Dist: pytest-cov>=4.0.0; extra == 'dev'
Requires-Dist: pytest-mock>=3.10.0; extra == 'dev'
Requires-Dist: pytest>=7.0.0; extra == 'dev'
Requires-Dist: requests-mock>=1.11.0; extra == 'dev'
Requires-Dist: ruff>=0.1.0; extra == 'dev'
